intellipandora-1.1.0.data/scripts/runner.py
ipandora/CHANGELOG
ipandora/__init__.py
ipandora/version.py
ipandora/common/__init__.py
ipandora/common/dictutils.py
ipandora/common/mysqlaction.py
ipandora/common/stringaction.py
ipandora/common/systeminfo.py
ipandora/common/timeutils.py
ipandora/common/uuidutils.py
ipandora/conf/__init__.py
ipandora/core/__init__.py
ipandora/core/base/__init__.py
ipandora/core/base/classwrap/__init__.py
ipandora/core/base/classwrap/attrvaluesplit.py
ipandora/core/base/classwrap/classproperty.py
ipandora/core/base/classwrap/multihandle.py
ipandora/core/base/classwrap/singleton.py
ipandora/core/base/data/__init__.py
ipandora/core/base/data/markdata.py
ipandora/core/base/loglib/__init__.py
ipandora/core/base/loglib/log.py
ipandora/core/base/repository/__init__.py
ipandora/core/base/repository/baserepository.py
ipandora/core/engine/__init__.py
ipandora/core/engine/crypto/__init__.py
ipandora/core/engine/crypto/aescryptographer.py
ipandora/core/engine/crypto/crypto.py
ipandora/core/engine/crypto/cryptoabc.py
ipandora/core/engine/crypto/fercryptographer.py
ipandora/core/engine/crypto/rsacryptographer.py
ipandora/core/engine/generator/__init__.py
ipandora/core/engine/generator/model/__init__.py
ipandora/core/engine/generator/model/data/__init__.py
ipandora/core/engine/generator/model/data/moduledata.py
ipandora/core/engine/generator/model/data/robotcase.py
ipandora/core/engine/generator/model/data/robotcaselegacy.py
ipandora/core/engine/generator/model/data/robotsuite.py
ipandora/core/engine/generator/model/data/robotsuitelegacy.py
ipandora/core/engine/generator/model/data/testcase.py
ipandora/core/engine/generator/model/handler/__init__.py
ipandora/core/engine/generator/model/handler/robotrenderer.py
ipandora/core/engine/generator/model/handler/robotrendererlegacy.py
ipandora/core/engine/generator/provider/__init__.py
ipandora/core/engine/generator/provider/caseprovider.py
ipandora/core/engine/generator/provider/robotbaseprovider.py
intellipandora-1.1.0.dist-info/AUTHORS.rst
intellipandora-1.1.0.dist-info/LICENSE
intellipandora-1.1.0.dist-info/METADATA
intellipandora-1.1.0.dist-info/WHEEL
intellipandora-1.1.0.dist-info/entry_points.txt
intellipandora-1.1.0.dist-info/top_level.txt
intellipandora-1.1.0.dist-info/RECORD
