Metadata-Version: 2.1
Name: intellipandora
Version: 1.1.0
Summary: Generic automation framework for system testing and model evaluation
Home-page: https://github.com/Conan-Shao/IntelliPandora
Author: Shao Feng
Author-email: just.shao.007@gmail.com
License: Apache License 2.0
Keywords: intellipandora
Classifier: Development Status :: 4 - Beta
Classifier: License :: OSI Approved :: Apache Software License
Classifier: Operating System :: OS Independent
Classifier: Programming Language :: Python :: 3
Classifier: Programming Language :: Python :: 3 :: Only
Classifier: Programming Language :: Python :: 3.8
Classifier: Programming Language :: Python :: 3.9
Classifier: Programming Language :: Python :: 3.10
Classifier: Programming Language :: Python :: 3.11
Classifier: Programming Language :: Python :: 3.12
Classifier: Programming Language :: Python :: Implementation :: CPython
Classifier: Topic :: Software Development :: Testing
Classifier: Topic :: Software Development :: Testing :: Acceptance
Classifier: Topic :: Software Development :: Testing :: BDD
Classifier: Topic :: Software Development :: Libraries :: Python Modules
Classifier: Topic :: Utilities
Classifier: Framework :: Robot Framework
Classifier: Framework :: Pytest
Requires-Python: >=3.7
License-File: LICENSE
License-File: AUTHORS.rst
Requires-Dist: twine
Requires-Dist: setuptools
Requires-Dist: six
Requires-Dist: pendulum
Requires-Dist: tabulate
Requires-Dist: retrying
Requires-Dist: assertpy
Requires-Dist: bs4
Requires-Dist: pluggy
Requires-Dist: PyYAML
Requires-Dist: cryptography
Requires-Dist: urllib3
Requires-Dist: requests
Requires-Dist: websockets
Requires-Dist: httpretty
Requires-Dist: pytest
Requires-Dist: robotframework
Requires-Dist: psutil
Requires-Dist: Jinja2
Requires-Dist: pymysql
